blackonnx/__init__.py
blackonnx/_version.py
blackonnx/onnx_utils.py
blackonnx/utils.py
blackonnx/fix/__init__.py
blackonnx/fix/common_fix.py
blackonnx/fix/postprocess_fix.py
blackonnx/fix/quantize_fix.py
blackonnx-1.0.0.data/scripts/blackonnx
blackonnx-1.0.0.dist-info/LICENCE
blackonnx-1.0.0.dist-info/METADATA
blackonnx-1.0.0.dist-info/WHEEL
blackonnx-1.0.0.dist-info/top_level.txt
blackonnx-1.0.0.dist-info/RECORD
