Metadata-Version: 2.1
Name: blackonnx
Version: 1.0.0
Summary: Adapt ONNX models to enable nnoir conversion
Home-page: https://github.com/Idein/nnoir/tree/master/blackonnx
Author: Idein Inc.
Author-email: christian@idein.jp
License: MIT
Keywords: Adapt ONNX models to enable nnoir conversion
Platform: UNKNOWN
Classifier: Development Status :: 4 - Beta
Classifier: Intended Audience :: Developers
Classifier: License :: OSI Approved :: MIT License
Classifier: Programming Language :: Python :: 3 :: Only
Requires-Python: >=3.6.*
Requires-Dist: numpy
Requires-Dist: onnx
Requires-Dist: nnoir-onnx
